mems/MemsClient.py
mems/MemsEmulator.py
mems/MemsReader.py
mems/__init__.py
mems/interfaces/MemsSerialInterface.py
mems/interfaces/SerialInterface.py
mems/protocol/Rosco.py
memsulator-1.0.3.dist-info/LICENSE
memsulator-1.0.3.dist-info/METADATA
memsulator-1.0.3.dist-info/WHEEL
memsulator-1.0.3.dist-info/top_level.txt
memsulator-1.0.3.dist-info/RECORD
