Metadata-Version: 2.1
Name: memsulator
Version: 1.0.3
Summary: Rover MEMS 1.6 Serial Interface and Emulator
Home-page: http://github.com/andrewdjackson/memsulator
Author: Andrew Jackson
Author-email: andrew.d.jackson@gmail.com
License: MIT
Platform: UNKNOWN
